aaio/__init__.py
aaio/client.py
aaio/utils.py
aaio/exceptions/__init__.py
aaio/exceptions/bad_request.py
aaio/models/__init__.py
aaio/models/balance.py
aaio/models/create_payoff.py
aaio/models/payment_info.py
aaio/models/payment_methods.py
aaio/models/payment_webhook.py
aaio/models/payoff_info.py
aaio/models/payoff_methods.py
aaio/models/payoff_rates.py
aaio/models/payoff_sbp_banks.py
aaio/models/payoff_webhook.py
aaio-1.4.2.dist-info/METADATA
aaio-1.4.2.dist-info/WHEEL
aaio-1.4.2.dist-info/licenses/LICENSE
aaio-1.4.2.dist-info/RECORD
