Metadata-Version: 2.3
Name: aaio
Version: 1.4.2
Summary: Async AAIO api wrapper for python
Project-URL: Homepage, https://github.com/kewldan/AAIO
Author-email: kewldan <kewldanil1@gmail.com>
License: MIT License
License-File: LICENSE
Keywords: api,payments
Classifier: License :: OSI Approved :: MIT License
Classifier: Programming Language :: Python
Classifier: Programming Language :: Python :: 3
Requires-Python: >=3.7
Requires-Dist: aiohttp
Requires-Dist: pydantic
